pydagoras/__about__.py
pydagoras/__init__.py
pydagoras/dag.py
pydagoras/dag_dot.py
pydagoras/node.py
pydagoras-0.0.14.dist-info/METADATA
pydagoras-0.0.14.dist-info/WHEEL
pydagoras-0.0.14.dist-info/licenses/LICENSE
pydagoras-0.0.14.dist-info/RECORD
