Metadata-Version: 2.4
Name: pydagoras
Version: 0.0.14
Summary: A Direct Acyclic Graph lib
Project-URL: Documentation, https://markhallett.github.io/pydagoras/
Project-URL: Homepage, https://pydagoras.com
Project-URL: Source, https://github.com/MarkHallett/pydagoras
Author-email: Mark Hallett <pydagoras@markhallett.co.uk>
License: MIT
License-File: LICENSE
Classifier: Development Status :: 4 - Beta
Classifier: Programming Language :: Python
Classifier: Programming Language :: Python :: 3.8
Classifier: Programming Language :: Python :: 3.9
Classifier: Programming Language :: Python :: 3.10
Classifier: Programming Language :: Python :: 3.11
Classifier: Programming Language :: Python :: 3.12
Classifier: Programming Language :: Python :: Implementation :: CPython
Classifier: Programming Language :: Python :: Implementation :: PyPy
Requires-Python: >=3.8
Requires-Dist: pygraphviz
